radboy/.~lock.case-export-2024-05-14-13-10-00.672971.xlsx#
radboy/1-2024-04-02.png_04022024.jpg
radboy/Default.TTF
radboy/Holidays.txt
radboy/InventoryGlossary.txt
radboy/RecordMyCodes.py
radboy/Run.py
radboy/__init__.py
radboy/api_key
radboy/case-export-2024-05-14-13-10-00.672971.xlsx
radboy/case-export-2024-05-14-13-13-22.540614.xlsx
radboy/changelog.txt
radboy/code.png
radboy/db.csv
radboy/dictionary.txt
radboy/export.csv
radboy/helpMsg.txt
radboy/home.csv
radboy/nanoid.txt
radboy/possibleCode.py
radboy/renderQR.py
radboy/renderQR.py.README
radboy/renderQrRun.py
radboy/t.py
radboy/te.py
radboy/whatIs15.py
radboy/x.py
radboy/AlcoholConsumption/__init__.py
radboy/AlcoholConsumption/ac.py
radboy/AlcoholConsumption/__pycache__/__init__.cpython-312.pyc
radboy/AlcoholConsumption/__pycache__/__init__.cpython-313.pyc
radboy/AlcoholConsumption/__pycache__/ac.cpython-312.pyc
radboy/AlcoholConsumption/__pycache__/ac.cpython-313.pyc
radboy/BNC/BnC.py
radboy/BNC/__init__.py
radboy/BNC/__pycache__/BnC.cpython-312.pyc
radboy/BNC/__pycache__/BnC.cpython-313.pyc
radboy/BNC/__pycache__/__init__.cpython-312.pyc
radboy/BNC/__pycache__/__init__.cpython-313.pyc
radboy/Collector2/Collector2.py
radboy/Collector2/__init__.py
radboy/Collector2/__pycache__/Collector2.cpython-311.pyc
radboy/Collector2/__pycache__/Collector2.cpython-312.pyc
radboy/Collector2/__pycache__/Collector2.cpython-313.pyc
radboy/Collector2/__pycache__/__init__.cpython-311.pyc
radboy/Collector2/__pycache__/__init__.cpython-312.pyc
radboy/Collector2/__pycache__/__init__.cpython-313.pyc
radboy/Comm/RxTx.py
radboy/Comm/__init__.py
radboy/Comm/__pycache__/RxTx.cpython-312.pyc
radboy/Comm/__pycache__/RxTx.cpython-313.pyc
radboy/Comm/__pycache__/__init__.cpython-312.pyc
radboy/Comm/__pycache__/__init__.cpython-313.pyc
radboy/Comm2Common/Comm2Common.py
radboy/Comm2Common/__init__.py
radboy/Compare/Compare.py
radboy/Compare/__init__.py
radboy/Compare/__pycache__/Compare.cpython-312.pyc
radboy-0.0.949.dist-info/METADATA
radboy-0.0.949.dist-info/WHEEL
radboy-0.0.949.dist-info/top_level.txt
radboy-0.0.949.dist-info/RECORD
