Metadata-Version: 2.4
Name: radboy
Version: 0.0.949
Summary: A Retail Calculator for Android/Linux
Author: Carl Joseph Hirner III
Author-email: Carl Hirner III <k.j.hirner.wisdom@gmail.com>
License-Expression: MIT
Project-URL: Homepage, https://google.com
Project-URL: Issues, https://google.com
Classifier: Programming Language :: Python :: 3
Classifier: Operating System :: OS Independent
Requires-Python: >=3.6
Requires-Dist: scipy
Requires-Dist: inputimeout
Requires-Dist: gdown
Requires-Dist: biip
Requires-Dist: sympy
Requires-Dist: scipy
Requires-Dist: plotext
Requires-Dist: haversine
Requires-Dist: holidays
Requires-Dist: odfpy
Requires-Dist: qrcode[pil]
Requires-Dist: chardet
Requires-Dist: nanoid
Requires-Dist: random-password-generator
Requires-Dist: cython
Requires-Dist: pint
Requires-Dist: pyupc-ean
Requires-Dist: openpyxl
Requires-Dist: plyer
Requires-Dist: colored
Requires-Dist: numpy
Requires-Dist: pandas
Requires-Dist: Pillow
Requires-Dist: python-barcode
Requires-Dist: qrcode
Requires-Dist: requests
Requires-Dist: sqlalchemy
Requires-Dist: argparse
Requires-Dist: geocoder
Requires-Dist: beautifulsoup4
Requires-Dist: pycryptodome
Requires-Dist: forecast_weather
Requires-Dist: boozelib
Requires-Dist: pint_pandas
Requires-Dist: xlsxwriter
Requires-Dist: chemlib
Requires-Dist: chemicals
Requires-Dist: chempy
Requires-Dist: magpylib
Requires-Dist: humanfriendly
Provides-Extra: linux
Requires-Dist: gnureadline; extra == "linux"
Provides-Extra: android
Requires-Dist: readline; extra == "android"
Dynamic: author
Dynamic: requires-python
